t2wml/__init__.py
t2wml/api.py
t2wml/knowledge_graph.py
t2wml/project.py
t2wml/settings.py
t2wml/__pycache__/__init__.cpython-38.pyc
t2wml/input_processing/__init__.py
t2wml/input_processing/annotation_parsing.py
t2wml/input_processing/annotation_suggesting.py
t2wml/input_processing/clean_yaml_parsing.py
t2wml/input_processing/node_creation.py
t2wml/input_processing/region.py
t2wml/input_processing/utils.py
t2wml/input_processing/yaml_parsing.py
t2wml/mapping/__init__.py
t2wml/mapping/canonical_spreadsheet.py
t2wml/mapping/datamart_edges.py
t2wml/mapping/kgtk.py
t2wml/mapping/statement_mapper.py
t2wml/mapping/statements.py
t2wml/outputs/__init__.py
t2wml/outputs/canonical_spreadsheet.py
t2wml/outputs/datamart_edges.py
t2wml/outputs/kgtk.py
t2wml/parsing/__init__.py
t2wml/parsing/classes.py
t2wml/parsing/cleaning_functions.py
t2wml/parsing/constants.py
t2wml/parsing/t2wml_parsing.py
t2wml/parsing/template_functions.py
t2wml/spreadsheets/__init__.py
t2wml/spreadsheets/caching.py
t2wml/spreadsheets/conversions.py
t2wml/spreadsheets/sheet.py
t2wml/spreadsheets/utilities.py
t2wml/utils/__init__.py
t2wml/utils/bindings.py
t2wml/utils/date_utils.py
t2wml/utils/debug_logging.py
t2wml/utils/ethiopian_date.py
t2wml/utils/t2wml_exceptions.py
t2wml/utils/__pycache__/__init__.cpython-38.pyc
t2wml/utils/__pycache__/date_utils.cpython-38.pyc
t2wml/wikification/__init__.py
t2wml/wikification/country_wikifier_cache.py
t2wml/wikification/item_table.py
t2wml/wikification/new_item_table.py
t2wml/wikification/preloaded_properties.py
t2wml/wikification/preloaded_properties.tsv
t2wml/wikification/utility_functions.py
t2wml/wikification/wikidata_provider.py
t2wml/wikification/wikifier_service.py
unit_tests/__init__.py
unit_tests/test_annotations.py
unit_tests/test_api_classes.py
unit_tests/test_api_scripts.py
unit_tests/test_cleaning_functions.py
unit_tests/test_ethiopian_date.py
unit_tests/test_json_results.py
unit_tests/test_kgtk_results.py
unit_tests/test_suggestion.py
t2wml_api-0.6.6.dist-info/LICENSE
t2wml_api-0.6.6.dist-info/METADATA
t2wml_api-0.6.6.dist-info/WHEEL
t2wml_api-0.6.6.dist-info/top_level.txt
t2wml_api-0.6.6.dist-info/RECORD
