Metadata-Version: 2.1
Name: t2wml-api
Version: 0.6.6
Summary: Programming API for T2WML, a cell-based Language for mapping tables into wikidata records
Home-page: https://github.com/usc-isi-i2/t2wml/
Author: USC ISI and The Research Software Company
License: UNKNOWN
Platform: UNKNOWN
Classifier: Programming Language :: Python :: 3
Requires-Python: >=3.7
Requires-Dist: PyYAML (>=5.1.2)
Requires-Dist: numpy (==1.19.1)
Requires-Dist: pandas (==1.2.2)
Requires-Dist: SPARQLWrapper (>=1.8.5)
Requires-Dist: ftfy (>=5.8)
Requires-Dist: requests (>=2.24.0)
Requires-Dist: xlrd (>=1.0.0)
Requires-Dist: text-unidecode (==1.3)
Requires-Dist: munkres (==1.1.4)
